equilibrium/__init__.py
equilibrium/logger.py
equilibrium/modspec.py
equilibrium/settings.py
equilibrium/blocks/__init__.py
equilibrium/blocks/macro.py
equilibrium/blocks/symbolic.py
equilibrium/cli/__init__.py
equilibrium/cli/main.py
equilibrium/cli/scaffold.py
equilibrium/core/__init__.py
equilibrium/core/codegen.py
equilibrium/core/rules.py
equilibrium/io/__init__.py
equilibrium/io/results.py
equilibrium/model/__init__.py
equilibrium/model/linear.py
equilibrium/model/model.py
equilibrium/plot/__init__.py
equilibrium/plot/plot.py
equilibrium/solvers/__init__.py
equilibrium/solvers/calibration.py
equilibrium/solvers/det_spec.py
equilibrium/solvers/deterministic.py
equilibrium/solvers/linear.py
equilibrium/solvers/linear_spec.py
equilibrium/solvers/newton.py
equilibrium/solvers/perturb.py
equilibrium/solvers/results.py
equilibrium/templates/__init__.py
equilibrium/templates/base.py.jinja
equilibrium/templates/functions.py.jinja
equilibrium/templates/project_scaffold/.env.template
equilibrium/templates/project_scaffold/constants.py.template
equilibrium/templates/project_scaffold/main.py.template
equilibrium/templates/project_scaffold/model.py.template
equilibrium/templates/project_scaffold/parameters.py.template
equilibrium/utils/__init__.py
equilibrium/utils/containers.py
equilibrium/utils/io.py
equilibrium/utils/jax_function_bundle.py
equilibrium/utils/utilities.py
equilibrium-0.0.2.dist-info/METADATA
equilibrium-0.0.2.dist-info/WHEEL
equilibrium-0.0.2.dist-info/entry_points.txt
equilibrium-0.0.2.dist-info/licenses/LICENSE
equilibrium-0.0.2.dist-info/RECORD
