Metadata-Version: 2.4
Name: equilibrium
Version: 0.0.2
Summary: Dynamic general-equilibrium solver using JAX
Author-email: Daniel Greenwald <daniel.greenwald@stern.nyu.edu>
License: GPL-3.0-only
License-File: LICENSE
Requires-Python: >=3.10
Requires-Dist: black
Requires-Dist: jax>=0.4
Requires-Dist: jaxlib>=0.4
Requires-Dist: jinja2
Requires-Dist: matplotlib
Requires-Dist: networkx
Requires-Dist: numpy>=1.26
Requires-Dist: platformdirs>=4
Requires-Dist: pydantic-settings>=2
Requires-Dist: pydantic>=2
Requires-Dist: scipy
Requires-Dist: sympy
Requires-Dist: tabulate
Provides-Extra: dev
Requires-Dist: mypy; extra == 'dev'
Requires-Dist: pre-commit; extra == 'dev'
Requires-Dist: pytest; extra == 'dev'
Requires-Dist: ruff; extra == 'dev'
